globalmart_api_ELT/__init__.py
globalmart_api_ELT/oops.py
api_data_fetchingpi-0.1.dist-info/METADATA
api_data_fetchingpi-0.1.dist-info/WHEEL
api_data_fetchingpi-0.1.dist-info/top_level.txt
api_data_fetchingpi-0.1.dist-info/RECORD
